AUTHORS.rst
LICENSE
MANIFEST.in
README.rst
setup.cfg
setup.py
filteralchemy/__init__.py
filteralchemy/filters.py
filteralchemy/filterset.py
filteralchemy/formatters.py
filteralchemy/operators.py
filteralchemy/utils.py
filteralchemy_fork.egg-info/PKG-INFO
filteralchemy_fork.egg-info/SOURCES.txt
filteralchemy_fork.egg-info/dependency_links.txt
filteralchemy_fork.egg-info/not-zip-safe
filteralchemy_fork.egg-info/requires.txt
filteralchemy_fork.egg-info/top_level.txt