Metadata-Version: 1.1
Name: filteralchemy-fork
Version: 0.1.0
Summary: Declarative query builder for SQLAlchemy. This is a fork of the original project with the changes of https://github.com/jmcarp/filteralchemy/pull/2 applied
Home-page: https://github.com/infobyte/filteralchemy
Author: Matias Lang
Author-email: shareman1204@gmail.com
License: Copyright 2015 Joshua Carp
